{
  "_description": "FrankX Suno Music Inventory",
  "_sunoProfileUrl": "https://suno.com/@frankx",
  "_profileStats": {
    "followers": 483,
    "following": 183,
    "hooks": "17K",
    "likes": "1.4K",
    "bio": "Music to unleash your creative genius 🎼🎶🧠 Connecting visionaries",
    "styles": [
      "warm",
      "vocal",
      "tech house",
      "bassline",
      "hypnotic"
    ]
  },
  "_lastUpdated": "2026-03-02",
  "_count": 65,
  "_estimatedTotal": 500,
  "_note": "Only publicly visible songs scraped. Full library requires Suno authentication.",
  "_playlists": [
    {
      "name": "Golden Frequencies",
      "songs": 9,
      "url": "https://suno.com/playlist/77e7f75f-24b4-4c8f-b02c-10eff76a7052"
    },
    {
      "name": "Meditation",
      "songs": 1,
      "url": "https://suno.com/playlist/0bc7abe1-b2c7-41c9-98a2-c0fbf59dca1f"
    },
    {
      "name": "German Poets",
      "songs": 1,
      "url": "https://suno.com/playlist/2d655032-9006-45ce-9267-9d59def06ce7"
    },
    {
      "name": "Way of Water",
      "songs": 2,
      "url": "https://suno.com/playlist/2044d23d-3253-4a46-940b-7c10d9dc81ed"
    },
    {
      "name": "vibe",
      "songs": 1,
      "url": "https://suno.com/playlist/1532430a-1550-45ac-b298-dbde8f0e9e17"
    },
    {
      "name": "Peace For Your Soul",
      "songs": 1,
      "url": "https://suno.com/playlist/26136df0-7e47-460d-a0fe-be24ab69475d"
    },
    {
      "name": "Instrumental Magic",
      "songs": 3,
      "url": "https://suno.com/playlist/3b265675-b95e-48ec-a2ed-140f6962c54d"
    },
    {
      "name": "Arcanean Choir",
      "songs": 2,
      "url": "https://suno.com/playlist/898c6c67-1b25-495f-82ce-53d9139d9a25"
    },
    {
      "name": "Orchestral Beauty",
      "songs": 1,
      "url": "https://suno.com/playlist/0625352a-74c5-478a-933e-1204549efd36"
    }
  ],
  "_personas": [
    "Dadada Weihnachtszeit",
    "All In",
    "Suno Swims",
    "Growth",
    "Oh Arcanea D&B",
    "Green light",
    "Russian Punk",
    "Trust Trap Duo",
    "Fight Hop"
  ],
  "tracks": [
    {
      "id": "art-of-soulful-living",
      "type": "music",
      "title": "Art Of Soulful Living",
      "brand": "frankx",
      "status": "published",
      "tags": [
        "Rock",
        "Edm",
        "Drum And Bass"
      ],
      "platform": "suno",
      "sunoId": "3faa6621-9edb-441f-9ba9-279be2716bba",
      "sunoUrl": "https://suno.com/song/3faa6621-9edb-441f-9ba9-279be2716bba",
      "duration": "3:44",
      "genre": [
        "Rock",
        "Edm",
        "Drum And Bass"
      ],
      "plays": 18,
      "likes": 4,
      "section": "featured",
      "audioUrl": "https://vbmwpibfe0yzx3fd.public.blob.vercel-storage.com/music/3faa6621-9edb-441f-9ba9-279be2716bba/3faa6621-9edb-441f-9ba9-279be2716bba.mp3"
    },
    {
      "id": "magical-times",
      "type": "music",
      "title": "Magical Times",
      "brand": "frankx",
      "status": "published",
      "tags": [
        "Symphonic"
      ],
      "platform": "suno",
      "sunoId": "74856905-1e50-419c-ad15-92081a743511",
      "sunoUrl": "https://suno.com/song/74856905-1e50-419c-ad15-92081a743511",
      "duration": "3:20",
      "genre": [
        "Symphonic"
      ],
      "plays": 29,
      "likes": 3,
      "section": "featured",
      "audioUrl": "https://vbmwpibfe0yzx3fd.public.blob.vercel-storage.com/music/74856905-1e50-419c-ad15-92081a743511/74856905-1e50-419c-ad15-92081a743511.mp3"
    },
    {
      "id": "trust-in-yourself",
      "type": "music",
      "title": "Trust in Yourself",
      "brand": "frankx",
      "status": "published",
      "tags": [
        "Pop Punk",
        "Pop",
        "Symphonic"
      ],
      "platform": "suno",
      "sunoId": "66572f21-2682-41f3-9051-86446e9b9bd7",
      "sunoUrl": "https://suno.com/song/66572f21-2682-41f3-9051-86446e9b9bd7",
      "duration": "2:18",
      "genre": [
        "Pop Punk",
        "Pop",
        "Symphonic"
      ],
      "plays": 70,
      "likes": 34,
      "section": "featured",
      "audioUrl": "https://vbmwpibfe0yzx3fd.public.blob.vercel-storage.com/music/66572f21-2682-41f3-9051-86446e9b9bd7/66572f21-2682-41f3-9051-86446e9b9bd7.mp3"
    },
    {
      "id": "starlight-delight-remastered",
      "type": "music",
      "title": "Starlight Delight (Remastered)",
      "brand": "frankx",
      "status": "published",
      "tags": [
        "Pop",
        "Bassline",
        "Drum And Bass"
      ],
      "platform": "suno",
      "sunoId": "2d33b5c5-94b1-418b-8bc8-26d77e12dc92",
      "sunoUrl": "https://suno.com/song/2d33b5c5-94b1-418b-8bc8-26d77e12dc92",
      "duration": "2:59",
      "genre": [
        "Pop",
        "Bassline",
        "Drum And Bass"
      ],
      "plays": 86,
      "likes": 20,
      "section": "featured",
      "audioUrl": "https://vbmwpibfe0yzx3fd.public.blob.vercel-storage.com/music/2d33b5c5-94b1-418b-8bc8-26d77e12dc92/2d33b5c5-94b1-418b-8bc8-26d77e12dc92.mp3"
    },
    {
      "id": "the-awakening",
      "type": "music",
      "title": "The Awakening",
      "brand": "frankx",
      "status": "published",
      "tags": [
        "World"
      ],
      "platform": "suno",
      "sunoId": "8374d2ad-9142-4900-9028-a1e805688407",
      "sunoUrl": "https://suno.com/song/8374d2ad-9142-4900-9028-a1e805688407",
      "duration": "1:57",
      "genre": [
        "World"
      ],
      "plays": 134,
      "likes": 20,
      "section": "featured",
      "audioUrl": "https://vbmwpibfe0yzx3fd.public.blob.vercel-storage.com/music/8374d2ad-9142-4900-9028-a1e805688407/8374d2ad-9142-4900-9028-a1e805688407.mp3"
    },
    {
      "id": "vibe-os-track",
      "type": "music",
      "title": "Vibe O S",
      "brand": "frankx",
      "status": "published",
      "tags": [
        "Female Hip Hop"
      ],
      "platform": "suno",
      "sunoId": "9cbad174-9276-427f-9aed-1ba00c7db3db",
      "sunoUrl": "https://suno.com/song/9cbad174-9276-427f-9aed-1ba00c7db3db",
      "duration": "4:00",
      "genre": [
        "Female Hip Hop"
      ],
      "plays": 128,
      "likes": 24,
      "section": "featured",
      "relatedProduct": "vibe-os",
      "audioUrl": "https://vbmwpibfe0yzx3fd.public.blob.vercel-storage.com/music/9cbad174-9276-427f-9aed-1ba00c7db3db/9cbad174-9276-427f-9aed-1ba00c7db3db.mp3"
    },
    {
      "id": "i-feel-the-vibe",
      "type": "music",
      "title": "I Feel the Vibe",
      "brand": "frankx",
      "status": "published",
      "tags": [
        "Female Hip Hop"
      ],
      "platform": "suno",
      "sunoId": "f4a7a0e3-5689-4f47-8100-792a73034b54",
      "sunoUrl": "https://suno.com/song/f4a7a0e3-5689-4f47-8100-792a73034b54",
      "duration": "2:34",
      "genre": [
        "Female Hip Hop"
      ],
      "plays": 56,
      "likes": 19,
      "section": "featured",
      "audioUrl": "https://vbmwpibfe0yzx3fd.public.blob.vercel-storage.com/music/f4a7a0e3-5689-4f47-8100-792a73034b54/f4a7a0e3-5689-4f47-8100-792a73034b54.mp3"
    },
    {
      "id": "lumina",
      "type": "music",
      "title": "Lumina",
      "brand": "frankx",
      "status": "published",
      "tags": [
        "Rock",
        "Soul",
        "Orchestral"
      ],
      "platform": "suno",
      "sunoId": "1fc13c04-a7b3-427d-bff0-cac92ee524ae",
      "sunoUrl": "https://suno.com/song/1fc13c04-a7b3-427d-bff0-cac92ee524ae",
      "duration": "4:12",
      "genre": [
        "Rock",
        "Soul",
        "Orchestral"
      ],
      "plays": 108,
      "likes": 16,
      "section": "featured",
      "audioUrl": "https://vbmwpibfe0yzx3fd.public.blob.vercel-storage.com/music/1fc13c04-a7b3-427d-bff0-cac92ee524ae/1fc13c04-a7b3-427d-bff0-cac92ee524ae.mp3"
    },
    {
      "id": "arcanea-light-me-up",
      "type": "music",
      "title": "Arcanea (light me up) (Remastered)",
      "brand": "frankx",
      "status": "published",
      "tags": [
        "Pop Rock",
        "Soul"
      ],
      "platform": "suno",
      "sunoId": "9ff8a563-4ebf-4481-85c1-9f445cfce9e1",
      "sunoUrl": "https://suno.com/song/9ff8a563-4ebf-4481-85c1-9f445cfce9e1",
      "duration": "3:07",
      "genre": [
        "Pop Rock",
        "Soul"
      ],
      "plays": 71,
      "likes": 10,
      "section": "featured",
      "crossReference": "arcanea/music.json",
      "audioUrl": "https://vbmwpibfe0yzx3fd.public.blob.vercel-storage.com/music/9ff8a563-4ebf-4481-85c1-9f445cfce9e1/9ff8a563-4ebf-4481-85c1-9f445cfce9e1.mp3"
    },
    {
      "id": "golden-age-of-intelligence",
      "type": "music",
      "title": "Golden Age of Intelligence",
      "brand": "frankx",
      "status": "published",
      "tags": [
        "Metalcore"
      ],
      "platform": "suno",
      "sunoId": "d1ad41a9-9239-454d-bc2c-a187f42ac30b",
      "sunoUrl": "https://suno.com/song/d1ad41a9-9239-454d-bc2c-a187f42ac30b",
      "duration": "2:34",
      "genre": [
        "Metalcore"
      ],
      "plays": 119,
      "likes": 20,
      "section": "featured",
      "relatedContent": [
        "golden-age-of-intelligence-book"
      ],
      "audioUrl": "https://vbmwpibfe0yzx3fd.public.blob.vercel-storage.com/music/d1ad41a9-9239-454d-bc2c-a187f42ac30b/d1ad41a9-9239-454d-bc2c-a187f42ac30b.mp3"
    },
    {
      "id": "golden-frequency-floor",
      "type": "music",
      "title": "Golden Frequency Floor",
      "brand": "frankx",
      "status": "published",
      "tags": [
        "Pop",
        "Drum And Bass",
        "Techno"
      ],
      "platform": "suno",
      "sunoId": "58fc5583-b33f-4c62-bbdc-d10dfc19de69",
      "sunoUrl": "https://suno.com/song/58fc5583-b33f-4c62-bbdc-d10dfc19de69",
      "genre": [
        "Pop",
        "Drum And Bass",
        "Techno"
      ],
      "plays": 5,
      "likes": 1,
      "section": "songs",
      "audioUrl": "https://vbmwpibfe0yzx3fd.public.blob.vercel-storage.com/music/58fc5583-b33f-4c62-bbdc-d10dfc19de69/58fc5583-b33f-4c62-bbdc-d10dfc19de69.mp3"
    },
    {
      "id": "beast-mode-switch",
      "type": "music",
      "title": "Beast Mode Switch",
      "brand": "frankx",
      "status": "published",
      "tags": [
        "Rap",
        "Trap"
      ],
      "platform": "suno",
      "sunoId": "e7f3ebea-55ae-428b-9add-cb9abdd08345",
      "sunoUrl": "https://suno.com/song/e7f3ebea-55ae-428b-9add-cb9abdd08345",
      "genre": [
        "Rap",
        "Trap"
      ],
      "plays": 5,
      "likes": 2,
      "section": "songs",
      "audioUrl": "https://vbmwpibfe0yzx3fd.public.blob.vercel-storage.com/music/e7f3ebea-55ae-428b-9add-cb9abdd08345/e7f3ebea-55ae-428b-9add-cb9abdd08345.mp3"
    },
    {
      "id": "magical-world-v3",
      "type": "music",
      "title": "Magical World v3",
      "brand": "frankx",
      "status": "published",
      "tags": [
        "Tech House",
        "Dance"
      ],
      "platform": "suno",
      "sunoId": "0f29d2c8-e0a7-4a67-bda6-d4baa200451e",
      "sunoUrl": "https://suno.com/song/0f29d2c8-e0a7-4a67-bda6-d4baa200451e",
      "genre": [
        "Tech House",
        "Dance"
      ],
      "plays": 10,
      "likes": 2,
      "section": "songs",
      "audioUrl": "https://vbmwpibfe0yzx3fd.public.blob.vercel-storage.com/music/0f29d2c8-e0a7-4a67-bda6-d4baa200451e/0f29d2c8-e0a7-4a67-bda6-d4baa200451e.mp3"
    },
    {
      "id": "i-want-to-build-a-free-world",
      "type": "music",
      "title": "I Want To Build A Free World",
      "brand": "frankx",
      "status": "published",
      "tags": [
        "Tech House"
      ],
      "platform": "suno",
      "sunoId": "d4fcd916-bfb2-4770-87c9-bd6257a00f2f",
      "sunoUrl": "https://suno.com/song/d4fcd916-bfb2-4770-87c9-bd6257a00f2f",
      "genre": [
        "Tech House"
      ],
      "plays": 26,
      "likes": 2,
      "section": "songs",
      "audioUrl": "https://vbmwpibfe0yzx3fd.public.blob.vercel-storage.com/music/d4fcd916-bfb2-4770-87c9-bd6257a00f2f/d4fcd916-bfb2-4770-87c9-bd6257a00f2f.mp3"
    },
    {
      "id": "i-want-to-be-free",
      "type": "music",
      "title": "I Want To Be Free",
      "brand": "frankx",
      "status": "published",
      "tags": [
        "Tech House"
      ],
      "platform": "suno",
      "sunoId": "353f6f50-f69d-4a72-8dbe-da58e59dcd73",
      "sunoUrl": "https://suno.com/song/353f6f50-f69d-4a72-8dbe-da58e59dcd73",
      "genre": [
        "Tech House"
      ],
      "plays": 12,
      "likes": 1,
      "section": "songs",
      "audioUrl": "https://vbmwpibfe0yzx3fd.public.blob.vercel-storage.com/music/353f6f50-f69d-4a72-8dbe-da58e59dcd73/353f6f50-f69d-4a72-8dbe-da58e59dcd73.mp3"
    },
    {
      "id": "feel-your-magic",
      "type": "music",
      "title": "Feel Your Magic",
      "brand": "frankx",
      "status": "published",
      "tags": [
        "Tech House"
      ],
      "platform": "suno",
      "sunoId": "f2c6fa51-1ac7-409d-8642-49d553dd8844",
      "sunoUrl": "https://suno.com/song/f2c6fa51-1ac7-409d-8642-49d553dd8844",
      "genre": [
        "Tech House"
      ],
      "plays": 18,
      "likes": 1,
      "section": "songs",
      "audioUrl": "https://vbmwpibfe0yzx3fd.public.blob.vercel-storage.com/music/f2c6fa51-1ac7-409d-8642-49d553dd8844/f2c6fa51-1ac7-409d-8642-49d553dd8844.mp3"
    },
    {
      "id": "need-to-feel-your-magic-v2",
      "type": "music",
      "title": "Need To Feel Your Magic v2",
      "brand": "frankx",
      "status": "published",
      "tags": [
        "Tech House"
      ],
      "platform": "suno",
      "sunoId": "8380e34f-d61c-47e9-ac17-3538a8c17d99",
      "sunoUrl": "https://suno.com/song/8380e34f-d61c-47e9-ac17-3538a8c17d99",
      "genre": [
        "Tech House"
      ],
      "plays": 12,
      "likes": 1,
      "section": "songs",
      "audioUrl": "https://vbmwpibfe0yzx3fd.public.blob.vercel-storage.com/music/8380e34f-d61c-47e9-ac17-3538a8c17d99/8380e34f-d61c-47e9-ac17-3538a8c17d99.mp3"
    },
    {
      "id": "create-millions-of-starlights",
      "type": "music",
      "title": "Create Millions of Starlights",
      "brand": "frankx",
      "status": "published",
      "tags": [
        "Rock",
        "Drum And Bass",
        "Punk"
      ],
      "platform": "suno",
      "sunoId": "b4db2632-d9ee-4924-9c21-e788b0339a15",
      "sunoUrl": "https://suno.com/song/b4db2632-d9ee-4924-9c21-e788b0339a15",
      "genre": [
        "Rock",
        "Drum And Bass",
        "Punk"
      ],
      "plays": 12,
      "likes": 1,
      "section": "songs",
      "audioUrl": "https://vbmwpibfe0yzx3fd.public.blob.vercel-storage.com/music/b4db2632-d9ee-4924-9c21-e788b0339a15/b4db2632-d9ee-4924-9c21-e788b0339a15.mp3"
    },
    {
      "id": "we-are-millions-of-starlights",
      "type": "music",
      "title": "We Are Millions of Starlights",
      "brand": "frankx",
      "status": "published",
      "tags": [
        "Dance"
      ],
      "platform": "suno",
      "sunoId": "e5fd662d-52d6-45d3-bc12-03ec02e85b43",
      "sunoUrl": "https://suno.com/song/e5fd662d-52d6-45d3-bc12-03ec02e85b43",
      "genre": [
        "Dance"
      ],
      "plays": 8,
      "likes": 1,
      "section": "songs",
      "audioUrl": "https://vbmwpibfe0yzx3fd.public.blob.vercel-storage.com/music/e5fd662d-52d6-45d3-bc12-03ec02e85b43/e5fd662d-52d6-45d3-bc12-03ec02e85b43.mp3"
    },
    {
      "id": "golden-frequencies-v4",
      "type": "music",
      "title": "Golden Frequencies v4",
      "brand": "frankx",
      "status": "published",
      "tags": [
        "Neoclassical",
        "Ambient"
      ],
      "platform": "suno",
      "sunoId": "3841ae2a-1147-4adb-8b4e-c0491d554fee",
      "sunoUrl": "https://suno.com/song/3841ae2a-1147-4adb-8b4e-c0491d554fee",
      "duration": "2:39",
      "genre": [
        "Neoclassical",
        "Ambient"
      ],
      "mood": [
        "meditative",
        "calming"
      ],
      "bpm": 128,
      "playlist": "Golden Frequencies",
      "audioUrl": "https://vbmwpibfe0yzx3fd.public.blob.vercel-storage.com/music/3841ae2a-1147-4adb-8b4e-c0491d554fee/3841ae2a-1147-4adb-8b4e-c0491d554fee.mp3"
    },
    {
      "id": "golden-frequency-choir-1",
      "type": "music",
      "title": "Golden Frequency Choir",
      "brand": "frankx",
      "status": "published",
      "tags": [
        "Neoclassical",
        "Choral",
        "World"
      ],
      "platform": "suno",
      "sunoId": "69fa45d3-8d45-4f6d-9424-9361cc95fe0a",
      "sunoUrl": "https://suno.com/song/69fa45d3-8d45-4f6d-9424-9361cc95fe0a",
      "duration": "3:26",
      "genre": [
        "Neoclassical",
        "Choral",
        "World"
      ],
      "playlist": "Golden Frequencies",
      "audioUrl": "https://vbmwpibfe0yzx3fd.public.blob.vercel-storage.com/music/69fa45d3-8d45-4f6d-9424-9361cc95fe0a/69fa45d3-8d45-4f6d-9424-9361cc95fe0a.mp3"
    },
    {
      "id": "golden-frequencies-v5",
      "type": "music",
      "title": "Golden Frequencies",
      "brand": "frankx",
      "status": "published",
      "tags": [
        "Neoclassical",
        "Ambient"
      ],
      "platform": "suno",
      "sunoId": "5281ac63-ed5a-4933-b8ae-10d2312f3c1a",
      "sunoUrl": "https://suno.com/song/5281ac63-ed5a-4933-b8ae-10d2312f3c1a",
      "duration": "3:07",
      "genre": [
        "Neoclassical",
        "Ambient"
      ],
      "playlist": "Golden Frequencies",
      "audioUrl": "https://vbmwpibfe0yzx3fd.public.blob.vercel-storage.com/music/5281ac63-ed5a-4933-b8ae-10d2312f3c1a/5281ac63-ed5a-4933-b8ae-10d2312f3c1a.mp3"
    },
    {
      "id": "golden-frequency-v3",
      "type": "music",
      "title": "Golden Frequency v3",
      "brand": "frankx",
      "status": "published",
      "tags": [
        "Neoclassical",
        "Choral"
      ],
      "platform": "suno",
      "sunoId": "721ba24a-ce51-4bba-82f2-83179a8d1ae4",
      "sunoUrl": "https://suno.com/song/721ba24a-ce51-4bba-82f2-83179a8d1ae4",
      "duration": "3:24",
      "genre": [
        "Neoclassical",
        "Choral"
      ],
      "playlist": "Golden Frequencies",
      "audioUrl": "https://vbmwpibfe0yzx3fd.public.blob.vercel-storage.com/music/721ba24a-ce51-4bba-82f2-83179a8d1ae4/721ba24a-ce51-4bba-82f2-83179a8d1ae4.mp3"
    },
    {
      "id": "golden-frequency-choir-native",
      "type": "music",
      "title": "Golden Frequency Choir (Native American)",
      "brand": "frankx",
      "status": "published",
      "tags": [
        "Neoclassical",
        "World",
        "Choral"
      ],
      "platform": "suno",
      "sunoId": "3a3f32dc-f5fc-4092-bd57-9dc6b2c574f9",
      "sunoUrl": "https://suno.com/song/3a3f32dc-f5fc-4092-bd57-9dc6b2c574f9",
      "duration": "3:31",
      "genre": [
        "Neoclassical",
        "World",
        "Choral"
      ],
      "playlist": "Golden Frequencies",
      "audioUrl": "https://vbmwpibfe0yzx3fd.public.blob.vercel-storage.com/music/3a3f32dc-f5fc-4092-bd57-9dc6b2c574f9/3a3f32dc-f5fc-4092-bd57-9dc6b2c574f9.mp3"
    },
    {
      "id": "golden-frequency-choir-male-native",
      "type": "music",
      "title": "Golden Frequency Choir (Male Native)",
      "brand": "frankx",
      "status": "published",
      "tags": [
        "Neoclassical",
        "World",
        "Choral"
      ],
      "platform": "suno",
      "sunoId": "266413cf-32a2-4d56-b143-25424244a025",
      "sunoUrl": "https://suno.com/song/266413cf-32a2-4d56-b143-25424244a025",
      "duration": "3:05",
      "genre": [
        "Neoclassical",
        "World",
        "Choral"
      ],
      "playlist": "Golden Frequencies",
      "audioUrl": "https://vbmwpibfe0yzx3fd.public.blob.vercel-storage.com/music/266413cf-32a2-4d56-b143-25424244a025/266413cf-32a2-4d56-b143-25424244a025.mp3"
    },
    {
      "id": "golden-frequency-choir-extended",
      "type": "music",
      "title": "Golden Frequency Choir (Extended)",
      "brand": "frankx",
      "status": "published",
      "tags": [
        "Neoclassical",
        "World",
        "Choral"
      ],
      "platform": "suno",
      "sunoId": "b1c58d80-f4d6-45aa-8ffc-c531be288a5a",
      "sunoUrl": "https://suno.com/song/b1c58d80-f4d6-45aa-8ffc-c531be288a5a",
      "duration": "4:46",
      "genre": [
        "Neoclassical",
        "World",
        "Choral"
      ],
      "playlist": "Golden Frequencies",
      "audioUrl": "https://vbmwpibfe0yzx3fd.public.blob.vercel-storage.com/music/b1c58d80-f4d6-45aa-8ffc-c531be288a5a/b1c58d80-f4d6-45aa-8ffc-c531be288a5a.mp3"
    },
    {
      "id": "golden-frequency-choir-mongolian",
      "type": "music",
      "title": "Golden Frequency Choir (Mongolian Lead)",
      "brand": "frankx",
      "status": "published",
      "tags": [
        "Neoclassical",
        "Electronic",
        "Choral"
      ],
      "platform": "suno",
      "sunoId": "8c35ffd4-193a-4955-832c-7a5be69b8604",
      "sunoUrl": "https://suno.com/song/8c35ffd4-193a-4955-832c-7a5be69b8604",
      "duration": "3:38",
      "genre": [
        "Neoclassical",
        "Electronic",
        "Choral"
      ],
      "playlist": "Golden Frequencies",
      "audioUrl": "https://vbmwpibfe0yzx3fd.public.blob.vercel-storage.com/music/8c35ffd4-193a-4955-832c-7a5be69b8604/8c35ffd4-193a-4955-832c-7a5be69b8604.mp3"
    },
    {
      "id": "golden-frequency-choir-mongolian-2",
      "type": "music",
      "title": "Golden Frequency Choir (Mongolian Harmonies)",
      "brand": "frankx",
      "status": "published",
      "tags": [
        "Neoclassical",
        "Electronic",
        "Choral"
      ],
      "platform": "suno",
      "sunoId": "1a6f3b3f-a207-4b8f-b2c4-03356c7b7e2b",
      "sunoUrl": "https://suno.com/song/1a6f3b3f-a207-4b8f-b2c4-03356c7b7e2b",
      "duration": "3:33",
      "genre": [
        "Neoclassical",
        "Electronic",
        "Choral"
      ],
      "playlist": "Golden Frequencies",
      "audioUrl": "https://vbmwpibfe0yzx3fd.public.blob.vercel-storage.com/music/1a6f3b3f-a207-4b8f-b2c4-03356c7b7e2b/1a6f3b3f-a207-4b8f-b2c4-03356c7b7e2b.mp3"
    },
    {
      "id": "arcanean-legends",
      "type": "music",
      "title": "Arcanean Legends",
      "brand": "frankx",
      "status": "published",
      "tags": [
        "Pop-rock",
        "Orchestral"
      ],
      "platform": "suno",
      "sunoId": "eb702834-22c6-44b3-8d5b-bba83c1e9801",
      "sunoUrl": "https://suno.com/song/eb702834-22c6-44b3-8d5b-bba83c1e9801",
      "duration": "3:24",
      "genre": [
        "Pop-rock",
        "Orchestral"
      ],
      "playlist": "Arcanean Choir",
      "crossReference": "arcanea/music.json",
      "audioUrl": "https://vbmwpibfe0yzx3fd.public.blob.vercel-storage.com/music/eb702834-22c6-44b3-8d5b-bba83c1e9801/eb702834-22c6-44b3-8d5b-bba83c1e9801.mp3"
    },
    {
      "id": "arcanean-starlight",
      "type": "music",
      "title": "Arcanean Starlight",
      "brand": "frankx",
      "status": "published",
      "tags": [
        "Arena-rock",
        "Orchestral"
      ],
      "platform": "suno",
      "sunoId": "5d17255b-f997-4f4c-82ea-9fa1d5aa982a",
      "sunoUrl": "https://suno.com/song/5d17255b-f997-4f4c-82ea-9fa1d5aa982a",
      "duration": "2:23",
      "genre": [
        "Arena-rock",
        "Orchestral"
      ],
      "playlist": "Arcanean Choir",
      "crossReference": "arcanea/music.json",
      "audioUrl": "https://vbmwpibfe0yzx3fd.public.blob.vercel-storage.com/music/5d17255b-f997-4f4c-82ea-9fa1d5aa982a/5d17255b-f997-4f4c-82ea-9fa1d5aa982a.mp3"
    },
    {
      "id": "open-the-arc",
      "type": "music",
      "title": "Open the Arc",
      "brand": "frankx",
      "status": "published",
      "tags": [
        "Orchestral",
        "Cinematic",
        "Epic"
      ],
      "platform": "suno",
      "sunoUrl": "https://suno.com/@frankx/hook/877a0eaf-59f5-4a69-ae22-c130794d0762",
      "section": "hooks",
      "genre": [
        "Orchestral",
        "Cinematic",
        "Epic"
      ],
      "sunoId": "877a0eaf-59f5-4a69-ae22-c130794d0762"
    },
    {
      "id": "children-of-the-sea",
      "type": "music",
      "title": "CHILDREN OF THE SEA - FESTIVAL ANTHEM v3",
      "brand": "frankx",
      "status": "published",
      "tags": [
        "EDM",
        "Dance"
      ],
      "platform": "suno",
      "sunoUrl": "https://suno.com/@frankx/hook/3398b525-7f99-40aa-a78d-988965451054",
      "section": "hooks",
      "genre": [
        "EDM",
        "Dance"
      ],
      "sunoId": "3398b525-7f99-40aa-a78d-988965451054"
    },
    {
      "id": "echoes-of-eternity",
      "type": "music",
      "title": "Echoes of Eternity (Remastered x2)",
      "brand": "frankx",
      "status": "published",
      "tags": [
        "Ambient",
        "Cinematic"
      ],
      "platform": "suno",
      "sunoUrl": "https://suno.com/@frankx/hook/3bd939ef-86f2-4568-ad8e-c3d81631b816",
      "section": "hooks",
      "genre": [
        "Ambient",
        "Cinematic"
      ],
      "sunoId": "3bd939ef-86f2-4568-ad8e-c3d81631b816"
    },
    {
      "id": "arcanea-awaken",
      "type": "music",
      "title": "Arcanea Awaken",
      "brand": "frankx",
      "status": "published",
      "tags": [
        "Electronic",
        "Dance"
      ],
      "platform": "suno",
      "sunoUrl": "https://suno.com/@frankx/hook/279c5cdc-7eaf-4d8e-8d0d-19f990672194",
      "section": "hooks",
      "crossReference": "arcanea/music.json",
      "genre": [
        "Electronic",
        "Dance"
      ],
      "sunoId": "279c5cdc-7eaf-4d8e-8d0d-19f990672194"
    },
    {
      "id": "still-right-here",
      "type": "music",
      "title": "遠くても / Still Right Here",
      "brand": "frankx",
      "status": "published",
      "tags": [
        "Vocal"
      ],
      "platform": "suno",
      "sunoId": "a0a74bce-7059-4422-bbb3-db7c5041f797",
      "sunoUrl": "https://suno.com/song/a0a74bce-7059-4422-bbb3-db7c5041f797",
      "genre": [
        "Vocal"
      ],
      "plays": 76,
      "likes": 30,
      "section": "songs",
      "coverUrl": "https://cdn2.suno.ai/video_upload_0a143cda-a115-4fd2-a4be-536b43a17afb_video_upload_0a143cda-a115-4fd2-a4be-536b43a17afb_cover_snapshot_0s_1770472325_image.jpeg",
      "audioUrl": "https://vbmwpibfe0yzx3fd.public.blob.vercel-storage.com/music/a0a74bce-7059-4422-bbb3-db7c5041f797/a0a74bce-7059-4422-bbb3-db7c5041f797.mp3"
    },
    {
      "id": "jump-like-this",
      "type": "music",
      "title": "Jump Like This",
      "brand": "frankx",
      "status": "published",
      "tags": [
        "Rap",
        "K-pop",
        "Pop",
        "Trap",
        "Vocal",
        "Punk"
      ],
      "platform": "suno",
      "sunoId": "a89aeb94-e4a6-4486-9325-ddbbb43d481f",
      "sunoUrl": "https://suno.com/song/a89aeb94-e4a6-4486-9325-ddbbb43d481f",
      "genre": [
        "Rap",
        "K-pop",
        "Pop",
        "Trap",
        "Vocal",
        "Punk"
      ],
      "plays": 9,
      "section": "songs",
      "coverUrl": "https://cdn2.suno.ai/image_a89aeb94-e4a6-4486-9325-ddbbb43d481f.jpeg",
      "likes": 2,
      "audioUrl": "https://vbmwpibfe0yzx3fd.public.blob.vercel-storage.com/music/a89aeb94-e4a6-4486-9325-ddbbb43d481f/a89aeb94-e4a6-4486-9325-ddbbb43d481f.mp3"
    },
    {
      "id": "growth",
      "type": "music",
      "title": "Growth",
      "brand": "frankx",
      "status": "published",
      "tags": [
        "Cinematic",
        "Gospel",
        "Hip-hop",
        "Metal",
        "Orchestral",
        "Pop",
        "Punk",
        "Rap",
        "Rock",
        "Soul",
        "Vocal",
        "Pop Rock"
      ],
      "platform": "suno",
      "sunoId": "5b91499d-9d35-47fb-a832-5dd37a503875",
      "sunoUrl": "https://suno.com/song/5b91499d-9d35-47fb-a832-5dd37a503875",
      "genre": [
        "Cinematic",
        "Gospel",
        "Hip-hop",
        "Metal",
        "Orchestral",
        "Pop",
        "Punk",
        "Rap",
        "Rock",
        "Soul",
        "Vocal",
        "Pop Rock"
      ],
      "plays": 29,
      "section": "songs",
      "coverUrl": "https://cdn2.suno.ai/video_gen_f854429a-4bd1-40b8-a1c0-6f6b6abb0961_video_upload_f854429a-4bd1-40b8-a1c0-6f6b6abb0961_cover_snapshot_0s_1765297502_image.jpeg",
      "likes": 2,
      "audioUrl": "https://vbmwpibfe0yzx3fd.public.blob.vercel-storage.com/music/5b91499d-9d35-47fb-a832-5dd37a503875/5b91499d-9d35-47fb-a832-5dd37a503875.mp3"
    },
    {
      "id": "you-told-me-why",
      "type": "music",
      "title": "You Told Me Why",
      "brand": "frankx",
      "status": "published",
      "tags": [
        "Country",
        "Emo",
        "Vocal",
        "Hip-hop",
        "Rap",
        "Soul",
        "R&b",
        "Gospel",
        "Pop"
      ],
      "platform": "suno",
      "sunoId": "654ece10-731f-4ede-9f09-3518a3a385fd",
      "sunoUrl": "https://suno.com/song/654ece10-731f-4ede-9f09-3518a3a385fd",
      "genre": [
        "Country",
        "Emo",
        "Vocal",
        "Hip-hop",
        "Rap",
        "Soul",
        "R&b",
        "Gospel",
        "Pop"
      ],
      "plays": 10,
      "section": "songs",
      "coverUrl": "https://cdn2.suno.ai/image_654ece10-731f-4ede-9f09-3518a3a385fd.jpeg",
      "likes": 1,
      "audioUrl": "https://vbmwpibfe0yzx3fd.public.blob.vercel-storage.com/music/654ece10-731f-4ede-9f09-3518a3a385fd/654ece10-731f-4ede-9f09-3518a3a385fd.mp3"
    },
    {
      "id": "arcanean-vibe-gods",
      "type": "music",
      "title": "Мы — Arcanean Vibe Gods",
      "brand": "frankx",
      "status": "published",
      "tags": [
        "Rap",
        "Bass",
        "Deep House",
        "House",
        "Metal",
        "Vocal",
        "Gospel",
        "Soul",
        "Hip Hop",
        "Drum And Bass",
        "Electronic"
      ],
      "platform": "suno",
      "sunoId": "e5bc4eb1-15e8-4ad9-8677-7b8b5b0abfa7",
      "sunoUrl": "https://suno.com/song/e5bc4eb1-15e8-4ad9-8677-7b8b5b0abfa7",
      "genre": [
        "Rap",
        "Bass",
        "Deep House",
        "House",
        "Metal",
        "Vocal",
        "Gospel",
        "Soul",
        "Hip Hop",
        "Drum And Bass",
        "Electronic"
      ],
      "plays": 29,
      "section": "songs",
      "coverUrl": "https://cdn2.suno.ai/e5bc4eb1-15e8-4ad9-8677-7b8b5b0abfa7_e286a770.jpeg",
      "likes": 3,
      "audioUrl": "https://vbmwpibfe0yzx3fd.public.blob.vercel-storage.com/music/e5bc4eb1-15e8-4ad9-8677-7b8b5b0abfa7/e5bc4eb1-15e8-4ad9-8677-7b8b5b0abfa7.mp3"
    },
    {
      "id": "vibe-gods-of-arcanea",
      "type": "music",
      "title": "Vibe Gods of Arcanea",
      "brand": "frankx",
      "status": "published",
      "tags": [
        "Rap",
        "Bass",
        "Deep House",
        "Drum And Bass",
        "House",
        "Hip Hop",
        "Vocal",
        "Soul",
        "Electronic"
      ],
      "platform": "suno",
      "sunoId": "83163f8a-bc3f-4f67-83e1-05c077472bd1",
      "sunoUrl": "https://suno.com/song/83163f8a-bc3f-4f67-83e1-05c077472bd1",
      "genre": [
        "Rap",
        "Bass",
        "Deep House",
        "Drum And Bass",
        "House",
        "Hip Hop",
        "Vocal",
        "Soul",
        "Electronic"
      ],
      "plays": 45,
      "section": "songs",
      "coverUrl": "https://cdn2.suno.ai/83163f8a-bc3f-4f67-83e1-05c077472bd1_5a36cd3a.jpeg",
      "likes": 2,
      "audioUrl": "https://vbmwpibfe0yzx3fd.public.blob.vercel-storage.com/music/83163f8a-bc3f-4f67-83e1-05c077472bd1/83163f8a-bc3f-4f67-83e1-05c077472bd1.mp3"
    },
    {
      "id": "ven-aqu",
      "type": "music",
      "title": "Ven Aquí",
      "brand": "frankx",
      "status": "published",
      "tags": [
        "Latin Tech House",
        "Vocal"
      ],
      "platform": "suno",
      "sunoId": "7c8bd184-d2b0-4b53-8b90-3cfbfc7b7d8e",
      "sunoUrl": "https://suno.com/song/7c8bd184-d2b0-4b53-8b90-3cfbfc7b7d8e",
      "genre": [
        "Latin Tech House",
        "Vocal"
      ],
      "plays": 36,
      "section": "songs",
      "coverUrl": "https://cdn2.suno.ai/video_gen_df9af488-11e6-4d5a-a91f-0653e29626e4_video_upload_df9af488-11e6-4d5a-a91f-0653e29626e4_cover_snapshot_0s_1770420058_image.jpeg",
      "likes": 1,
      "audioUrl": "https://vbmwpibfe0yzx3fd.public.blob.vercel-storage.com/music/7c8bd184-d2b0-4b53-8b90-3cfbfc7b7d8e/7c8bd184-d2b0-4b53-8b90-3cfbfc7b7d8e.mp3"
    },
    {
      "id": "wei-e-wunderzeit",
      "type": "music",
      "title": "Weiße Wunderzeit",
      "brand": "frankx",
      "status": "published",
      "tags": [
        "Pop",
        "Vocal"
      ],
      "platform": "suno",
      "sunoId": "2c5c730b-43b7-499c-a8cc-bade029bb9e4",
      "sunoUrl": "https://suno.com/song/2c5c730b-43b7-499c-a8cc-bade029bb9e4",
      "genre": [
        "Pop",
        "Vocal"
      ],
      "plays": 3,
      "section": "songs",
      "coverUrl": "https://cdn2.suno.ai/image_2c5c730b-43b7-499c-a8cc-bade029bb9e4.jpeg",
      "likes": 1,
      "audioUrl": "https://vbmwpibfe0yzx3fd.public.blob.vercel-storage.com/music/2c5c730b-43b7-499c-a8cc-bade029bb9e4/2c5c730b-43b7-499c-a8cc-bade029bb9e4.mp3"
    },
    {
      "id": "all-in",
      "type": "music",
      "title": "All In",
      "brand": "frankx",
      "status": "published",
      "tags": [
        "Rap",
        "Punk",
        "Vocal",
        "Gospel",
        "Metal",
        "Orchestral",
        "Rock",
        "Pop Rock",
        "Hip-hop"
      ],
      "platform": "suno",
      "sunoId": "57d126dd-0367-4535-8888-10937be86819",
      "sunoUrl": "https://suno.com/song/57d126dd-0367-4535-8888-10937be86819",
      "genre": [
        "Rap",
        "Punk",
        "Vocal",
        "Gospel",
        "Metal",
        "Orchestral",
        "Rock",
        "Pop Rock",
        "Hip-hop"
      ],
      "plays": 20,
      "section": "songs",
      "coverUrl": "https://cdn2.suno.ai/image_57d126dd-0367-4535-8888-10937be86819.jpeg",
      "likes": 1,
      "audioUrl": "https://vbmwpibfe0yzx3fd.public.blob.vercel-storage.com/music/57d126dd-0367-4535-8888-10937be86819/57d126dd-0367-4535-8888-10937be86819.mp3"
    },
    {
      "id": "magical-world-arcanea-remix-v4",
      "type": "music",
      "title": "Magical World (Arcanea Remix v4)",
      "brand": "frankx",
      "status": "published",
      "tags": [
        "Dance",
        "House",
        "Techno",
        "Funk",
        "Tech House",
        "Vocal",
        "Bass",
        "Bassline",
        "World"
      ],
      "platform": "suno",
      "sunoId": "90062ca7-cc19-4cdc-af8d-840180f26fc9",
      "sunoUrl": "https://suno.com/song/90062ca7-cc19-4cdc-af8d-840180f26fc9",
      "genre": [
        "Dance",
        "House",
        "Techno",
        "Funk",
        "Tech House",
        "Vocal",
        "Bass",
        "Bassline",
        "World"
      ],
      "plays": 4,
      "section": "songs",
      "coverUrl": "https://cdn2.suno.ai/90062ca7-cc19-4cdc-af8d-840180f26fc9_afdd31f1.jpeg",
      "likes": 1,
      "audioUrl": "https://vbmwpibfe0yzx3fd.public.blob.vercel-storage.com/music/90062ca7-cc19-4cdc-af8d-840180f26fc9/90062ca7-cc19-4cdc-af8d-840180f26fc9.mp3"
    },
    {
      "id": "la-la-voltage",
      "type": "music",
      "title": "La La Voltage",
      "brand": "frankx",
      "status": "published",
      "tags": [
        "Dance",
        "Bass",
        "Cinematic",
        "Deep House",
        "House",
        "K-pop",
        "Pop",
        "Vocal",
        "Minimal"
      ],
      "platform": "suno",
      "sunoId": "63503780-8ba6-4320-a94b-bc6586e31d13",
      "sunoUrl": "https://suno.com/song/63503780-8ba6-4320-a94b-bc6586e31d13",
      "genre": [
        "Dance",
        "Bass",
        "Cinematic",
        "Deep House",
        "House",
        "K-pop",
        "Pop",
        "Vocal",
        "Minimal"
      ],
      "plays": 4,
      "section": "songs",
      "coverUrl": "https://cdn2.suno.ai/image_63503780-8ba6-4320-a94b-bc6586e31d13.jpeg",
      "likes": 1,
      "audioUrl": "https://vbmwpibfe0yzx3fd.public.blob.vercel-storage.com/music/63503780-8ba6-4320-a94b-bc6586e31d13/63503780-8ba6-4320-a94b-bc6586e31d13.mp3"
    },
    {
      "id": "music-is-my-life-freedom-is-a-vibe-x-young-again-m",
      "type": "music",
      "title": "Music is my Life, Freedom is a Vibe x Young Again (Mashup)",
      "brand": "frankx",
      "status": "published",
      "tags": [
        "Pop",
        "Dance"
      ],
      "platform": "suno",
      "sunoId": "9aa01775-4430-41a0-8523-2e540aa48a4c",
      "sunoUrl": "https://suno.com/song/9aa01775-4430-41a0-8523-2e540aa48a4c",
      "genre": [
        "Pop",
        "Dance"
      ],
      "plays": 6,
      "section": "songs",
      "coverUrl": "https://cdn2.suno.ai/video_gen_cde86afa-70b6-422f-93e8-d2207906765c_video_upload_cde86afa-70b6-422f-93e8-d2207906765c_cover_snapshot_0s_1772310639_image.jpeg",
      "likes": 2,
      "audioUrl": "https://vbmwpibfe0yzx3fd.public.blob.vercel-storage.com/music/9aa01775-4430-41a0-8523-2e540aa48a4c/9aa01775-4430-41a0-8523-2e540aa48a4c.mp3"
    },
    {
      "id": "arcanea-it-feels-so-good-x-vibe-o-s-mashup-mashup-",
      "type": "music",
      "title": "Arcanea, It Feels So Good x Vibe O S (Mashup) (Mashup) x Young Again (Mashup)",
      "brand": "frankx",
      "status": "published",
      "tags": [
        "Electronic",
        "Dance"
      ],
      "platform": "suno",
      "sunoId": "c119ae26-a57d-42a2-882a-b871fd1409d7",
      "sunoUrl": "https://suno.com/song/c119ae26-a57d-42a2-882a-b871fd1409d7",
      "genre": [
        "Electronic",
        "Dance"
      ],
      "plays": 8,
      "section": "songs",
      "coverUrl": "https://cdn2.suno.ai/video_gen_a450f956-1fdf-4f03-bfb7-1a50bfe829a8_video_upload_a450f956-1fdf-4f03-bfb7-1a50bfe829a8_cover_snapshot_0s_1772311752_image.jpeg",
      "likes": 3,
      "audioUrl": "https://vbmwpibfe0yzx3fd.public.blob.vercel-storage.com/music/c119ae26-a57d-42a2-882a-b871fd1409d7/c119ae26-a57d-42a2-882a-b871fd1409d7.mp3"
    },
    {
      "id": "arcanea-it-feels-so-good-x-vibe-x-music-is-my-life",
      "type": "music",
      "title": "Arcanea, It Feels So Good x Vibe … x Music is my Life, Freedom is a Vi… (Mashup)",
      "brand": "frankx",
      "status": "published",
      "tags": [
        "Electronic",
        "Dance"
      ],
      "platform": "suno",
      "sunoId": "8863d758-d882-4745-a371-78ee515c6c2d",
      "sunoUrl": "https://suno.com/song/8863d758-d882-4745-a371-78ee515c6c2d",
      "genre": [
        "Electronic",
        "Dance"
      ],
      "plays": 5,
      "section": "songs",
      "coverUrl": "https://cdn2.suno.ai/image_8863d758-d882-4745-a371-78ee515c6c2d.jpeg",
      "likes": 1,
      "audioUrl": "https://vbmwpibfe0yzx3fd.public.blob.vercel-storage.com/music/8863d758-d882-4745-a371-78ee515c6c2d/8863d758-d882-4745-a371-78ee515c6c2d.mp3"
    },
    {
      "id": "arcanea-it-feels-so-good-x-vibe-o-s-mashup-mashup",
      "type": "music",
      "title": "Arcanea, It Feels So Good x Vibe O S (Mashup) (Mashup)",
      "brand": "frankx",
      "status": "published",
      "tags": [
        "Electronic",
        "Dance"
      ],
      "platform": "suno",
      "sunoId": "69e30121-c4b9-4b09-a76b-c2e88df0a074",
      "sunoUrl": "https://suno.com/song/69e30121-c4b9-4b09-a76b-c2e88df0a074",
      "genre": [
        "Electronic",
        "Dance"
      ],
      "plays": 8,
      "section": "songs",
      "coverUrl": "https://cdn2.suno.ai/image_69e30121-c4b9-4b09-a76b-c2e88df0a074.jpeg",
      "likes": 1,
      "audioUrl": "https://vbmwpibfe0yzx3fd.public.blob.vercel-storage.com/music/69e30121-c4b9-4b09-a76b-c2e88df0a074/69e30121-c4b9-4b09-a76b-c2e88df0a074.mp3"
    },
    {
      "id": "arcanea-it-feels-so-good-x-vibe-o-s-mashup-mashup",
      "type": "music",
      "title": "Arcanea, It Feels So Good x Vibe O S (Mashup) (Mashup)",
      "brand": "frankx",
      "status": "published",
      "tags": [
        "Electronic",
        "Dance"
      ],
      "platform": "suno",
      "sunoId": "ba5559f9-f6ce-465d-9b5b-ecc916e2cb45",
      "sunoUrl": "https://suno.com/song/ba5559f9-f6ce-465d-9b5b-ecc916e2cb45",
      "genre": [
        "Electronic",
        "Dance"
      ],
      "plays": 9,
      "section": "songs",
      "coverUrl": "https://cdn2.suno.ai/ba5559f9-f6ce-465d-9b5b-ecc916e2cb45_1394551c.jpeg",
      "likes": 2,
      "audioUrl": "https://vbmwpibfe0yzx3fd.public.blob.vercel-storage.com/music/ba5559f9-f6ce-465d-9b5b-ecc916e2cb45/ba5559f9-f6ce-465d-9b5b-ecc916e2cb45.mp3"
    },
    {
      "id": "arcanea-feels-so-good",
      "type": "music",
      "title": "Arcanea Feels So Good",
      "brand": "frankx",
      "status": "published",
      "tags": [
        "Dance",
        "Bass",
        "House",
        "K-pop",
        "Pop",
        "Tech House",
        "Minimal",
        "Vocal",
        "Orchestral"
      ],
      "platform": "suno",
      "sunoId": "a0ab75fe-f6f2-446e-ae15-fa088a1853e3",
      "sunoUrl": "https://suno.com/song/a0ab75fe-f6f2-446e-ae15-fa088a1853e3",
      "genre": [
        "Dance",
        "Bass",
        "House",
        "K-pop",
        "Pop",
        "Tech House",
        "Minimal",
        "Vocal",
        "Orchestral"
      ],
      "plays": 12,
      "section": "songs",
      "coverUrl": "https://cdn2.suno.ai/a0ab75fe-f6f2-446e-ae15-fa088a1853e3_76d187cd.jpeg",
      "likes": 1,
      "audioUrl": "https://vbmwpibfe0yzx3fd.public.blob.vercel-storage.com/music/a0ab75fe-f6f2-446e-ae15-fa088a1853e3/a0ab75fe-f6f2-446e-ae15-fa088a1853e3.mp3"
    },
    {
      "id": "arcanea-la-la-la-feels-so-good",
      "type": "music",
      "title": "Arcanea (La La La Feels So Good)",
      "brand": "frankx",
      "status": "published",
      "tags": [
        "Rock",
        "K-pop",
        "Pop",
        "Vocal",
        "Bass",
        "Orchestral",
        "Punk"
      ],
      "platform": "suno",
      "sunoId": "7b890756-b129-44ee-bdd4-5b33eaf8f34f",
      "sunoUrl": "https://suno.com/song/7b890756-b129-44ee-bdd4-5b33eaf8f34f",
      "genre": [
        "Rock",
        "K-pop",
        "Pop",
        "Vocal",
        "Bass",
        "Orchestral",
        "Punk"
      ],
      "plays": 10,
      "section": "songs",
      "coverUrl": "https://cdn2.suno.ai/image_7b890756-b129-44ee-bdd4-5b33eaf8f34f.jpeg",
      "likes": 1,
      "audioUrl": "https://vbmwpibfe0yzx3fd.public.blob.vercel-storage.com/music/7b890756-b129-44ee-bdd4-5b33eaf8f34f/7b890756-b129-44ee-bdd4-5b33eaf8f34f.mp3"
    },
    {
      "id": "module-3-drum-and-bass-version-1",
      "type": "music",
      "title": "Module 3 drum and bass version 1",
      "brand": "frankx",
      "status": "published",
      "tags": [
        "Drum And Bass"
      ],
      "platform": "suno",
      "sunoId": "ce0f395d-880e-4c62-b46e-20962d6f98e6",
      "sunoUrl": "https://suno.com/song/ce0f395d-880e-4c62-b46e-20962d6f98e6",
      "genre": [
        "Drum And Bass"
      ],
      "plays": 12,
      "section": "songs",
      "coverUrl": "https://cdn2.suno.ai/image_ce0f395d-880e-4c62-b46e-20962d6f98e6.jpeg",
      "audioUrl": "https://vbmwpibfe0yzx3fd.public.blob.vercel-storage.com/music/ce0f395d-880e-4c62-b46e-20962d6f98e6/ce0f395d-880e-4c62-b46e-20962d6f98e6.mp3"
    },
    {
      "id": "golden-frequency-choir",
      "type": "music",
      "title": "Golden Frequency Choir",
      "brand": "frankx",
      "status": "published",
      "tags": [
        "Choral",
        "Gospel",
        "Neoclassical"
      ],
      "platform": "suno",
      "sunoId": "b4b8622f-6d4d-4808-ac56-bbb4effd24a9",
      "sunoUrl": "https://suno.com/song/b4b8622f-6d4d-4808-ac56-bbb4effd24a9",
      "genre": [
        "Choral",
        "Gospel",
        "Neoclassical"
      ],
      "plays": 0,
      "section": "songs",
      "coverUrl": "https://cdn2.suno.ai/image_large_b4b8622f-6d4d-4808-ac56-bbb4effd24a9.jpeg",
      "audioUrl": "https://vbmwpibfe0yzx3fd.public.blob.vercel-storage.com/music/b4b8622f-6d4d-4808-ac56-bbb4effd24a9/b4b8622f-6d4d-4808-ac56-bbb4effd24a9.mp3"
    },
    {
      "id": "golden-frequency",
      "type": "music",
      "title": "Golden Frequency",
      "brand": "frankx",
      "status": "published",
      "tags": [
        "Healing",
        "Ambient",
        "Meditation"
      ],
      "platform": "suno",
      "sunoId": "d56a7f92-9578-4624-b06a-2a2f1ad5b4d1",
      "sunoUrl": "https://suno.com/song/d56a7f92-9578-4624-b06a-2a2f1ad5b4d1",
      "genre": [
        "Healing",
        "Ambient",
        "Meditation"
      ],
      "plays": 0,
      "section": "songs",
      "coverUrl": "https://cdn2.suno.ai/image_large_d56a7f92-9578-4624-b06a-2a2f1ad5b4d1.jpeg",
      "audioUrl": "https://vbmwpibfe0yzx3fd.public.blob.vercel-storage.com/music/d56a7f92-9578-4624-b06a-2a2f1ad5b4d1/d56a7f92-9578-4624-b06a-2a2f1ad5b4d1.mp3"
    },
    {
      "id": "alpha-meditation-v3",
      "type": "music",
      "title": "Alpha meditation v3",
      "brand": "frankx",
      "status": "published",
      "tags": [
        "Meditation",
        "Ambient",
        "Healing"
      ],
      "platform": "suno",
      "sunoId": "66a7e1d5-5b8c-4d4c-8964-68ab80d5a068",
      "sunoUrl": "https://suno.com/song/66a7e1d5-5b8c-4d4c-8964-68ab80d5a068",
      "genre": [
        "Meditation",
        "Ambient",
        "Healing"
      ],
      "plays": 0,
      "section": "songs",
      "coverUrl": "https://cdn2.suno.ai/image_large_66a7e1d5-5b8c-4d4c-8964-68ab80d5a068.jpeg",
      "audioUrl": "https://vbmwpibfe0yzx3fd.public.blob.vercel-storage.com/music/66a7e1d5-5b8c-4d4c-8964-68ab80d5a068/66a7e1d5-5b8c-4d4c-8964-68ab80d5a068.mp3"
    },
    {
      "id": "die-stadt-theodor-storm-1852",
      "type": "music",
      "title": "Die Stadt — Theodor Storm (1852)",
      "brand": "frankx",
      "status": "published",
      "tags": [
        "Classical",
        "Vocal",
        "Neoclassical"
      ],
      "platform": "suno",
      "sunoId": "0401cf9c-54b8-41f2-bfc6-c1e46f7d72e9",
      "sunoUrl": "https://suno.com/song/0401cf9c-54b8-41f2-bfc6-c1e46f7d72e9",
      "genre": [
        "Classical",
        "Vocal",
        "Neoclassical"
      ],
      "plays": 0,
      "section": "songs",
      "coverUrl": "https://cdn2.suno.ai/image_large_0401cf9c-54b8-41f2-bfc6-c1e46f7d72e9.jpeg",
      "audioUrl": "https://vbmwpibfe0yzx3fd.public.blob.vercel-storage.com/music/0401cf9c-54b8-41f2-bfc6-c1e46f7d72e9/0401cf9c-54b8-41f2-bfc6-c1e46f7d72e9.mp3"
    },
    {
      "id": "way-of-water",
      "type": "music",
      "title": "Way of Water",
      "brand": "frankx",
      "status": "published",
      "tags": [
        "Ambient",
        "Cinematic",
        "New Age"
      ],
      "platform": "suno",
      "sunoId": "a35e5052-0693-426f-8e5e-858c163282db",
      "sunoUrl": "https://suno.com/song/a35e5052-0693-426f-8e5e-858c163282db",
      "genre": [
        "Ambient",
        "Cinematic",
        "New Age"
      ],
      "plays": 0,
      "section": "songs",
      "coverUrl": "https://cdn2.suno.ai/image_large_a35e5052-0693-426f-8e5e-858c163282db.jpeg",
      "audioUrl": "https://vbmwpibfe0yzx3fd.public.blob.vercel-storage.com/music/a35e5052-0693-426f-8e5e-858c163282db/a35e5052-0693-426f-8e5e-858c163282db.mp3"
    },
    {
      "id": "the-way-of-water",
      "type": "music",
      "title": "The Way of Water",
      "brand": "frankx",
      "status": "published",
      "tags": [
        "Ambient",
        "Cinematic",
        "New Age"
      ],
      "platform": "suno",
      "sunoId": "a311fbf4-d87a-44ae-a499-0d13813db17a",
      "sunoUrl": "https://suno.com/song/a311fbf4-d87a-44ae-a499-0d13813db17a",
      "genre": [
        "Ambient",
        "Cinematic",
        "New Age"
      ],
      "plays": 0,
      "section": "songs",
      "coverUrl": "https://cdn2.suno.ai/image_large_a311fbf4-d87a-44ae-a499-0d13813db17a.jpeg",
      "audioUrl": "https://vbmwpibfe0yzx3fd.public.blob.vercel-storage.com/music/a311fbf4-d87a-44ae-a499-0d13813db17a/a311fbf4-d87a-44ae-a499-0d13813db17a.mp3"
    },
    {
      "id": "vibe-to-shine",
      "type": "music",
      "title": "Vibe to Shine",
      "brand": "frankx",
      "status": "published",
      "tags": [
        "Pop",
        "Electronic"
      ],
      "platform": "suno",
      "sunoId": "4e7fb514-7aa2-4ddd-aba0-859077386118",
      "sunoUrl": "https://suno.com/song/4e7fb514-7aa2-4ddd-aba0-859077386118",
      "genre": [
        "Pop",
        "Electronic"
      ],
      "plays": 0,
      "section": "songs",
      "coverUrl": "https://cdn2.suno.ai/image_large_4e7fb514-7aa2-4ddd-aba0-859077386118.jpeg",
      "audioUrl": "https://vbmwpibfe0yzx3fd.public.blob.vercel-storage.com/music/4e7fb514-7aa2-4ddd-aba0-859077386118/4e7fb514-7aa2-4ddd-aba0-859077386118.mp3"
    },
    {
      "id": "enchanted-echo",
      "type": "music",
      "title": "Enchanted Echo",
      "brand": "frankx",
      "status": "published",
      "tags": [
        "Electronic",
        "Ambient"
      ],
      "platform": "suno",
      "sunoId": "d2be5f1a-d27d-4c42-821c-1cf804d51279",
      "sunoUrl": "https://suno.com/song/d2be5f1a-d27d-4c42-821c-1cf804d51279",
      "genre": [
        "Electronic",
        "Ambient"
      ],
      "plays": 0,
      "section": "songs",
      "coverUrl": "https://cdn2.suno.ai/image_large_d2be5f1a-d27d-4c42-821c-1cf804d51279.jpeg",
      "audioUrl": "https://vbmwpibfe0yzx3fd.public.blob.vercel-storage.com/music/d2be5f1a-d27d-4c42-821c-1cf804d51279/d2be5f1a-d27d-4c42-821c-1cf804d51279.mp3"
    },
    {
      "id": "magic-show",
      "type": "music",
      "title": "Magic Show",
      "brand": "frankx",
      "status": "published",
      "tags": [
        "Pop",
        "Electronic"
      ],
      "platform": "suno",
      "sunoId": "afb1cd30-7aca-4edf-aa21-73db4766b132",
      "sunoUrl": "https://suno.com/song/afb1cd30-7aca-4edf-aa21-73db4766b132",
      "genre": [
        "Pop",
        "Electronic"
      ],
      "plays": 0,
      "section": "songs",
      "coverUrl": "https://cdn2.suno.ai/image_large_afb1cd30-7aca-4edf-aa21-73db4766b132.jpeg",
      "audioUrl": "https://vbmwpibfe0yzx3fd.public.blob.vercel-storage.com/music/afb1cd30-7aca-4edf-aa21-73db4766b132/afb1cd30-7aca-4edf-aa21-73db4766b132.mp3"
    },
    {
      "id": "high-flyer",
      "type": "music",
      "title": "High Flyer",
      "brand": "frankx",
      "status": "published",
      "tags": [
        "Pop",
        "Rock"
      ],
      "platform": "suno",
      "sunoId": "ced929d0-db1f-49a2-a2f9-be78fdc18087",
      "sunoUrl": "https://suno.com/song/ced929d0-db1f-49a2-a2f9-be78fdc18087",
      "genre": [
        "Pop",
        "Rock"
      ],
      "plays": 0,
      "section": "songs",
      "coverUrl": "https://cdn2.suno.ai/image_large_ced929d0-db1f-49a2-a2f9-be78fdc18087.jpeg",
      "audioUrl": "https://vbmwpibfe0yzx3fd.public.blob.vercel-storage.com/music/ced929d0-db1f-49a2-a2f9-be78fdc18087/ced929d0-db1f-49a2-a2f9-be78fdc18087.mp3"
    },
    {
      "id": "magical-times",
      "type": "music",
      "title": "Magical Times",
      "brand": "frankx",
      "status": "published",
      "tags": [
        "Symphonic",
        "Cinematic"
      ],
      "platform": "suno",
      "sunoId": "38b38a65-13c3-4f31-8ab0-78fd7b218c11",
      "sunoUrl": "https://suno.com/song/38b38a65-13c3-4f31-8ab0-78fd7b218c11",
      "genre": [
        "Symphonic",
        "Cinematic"
      ],
      "plays": 0,
      "section": "songs",
      "coverUrl": "https://cdn2.suno.ai/image_large_38b38a65-13c3-4f31-8ab0-78fd7b218c11.jpeg",
      "audioUrl": "https://vbmwpibfe0yzx3fd.public.blob.vercel-storage.com/music/38b38a65-13c3-4f31-8ab0-78fd7b218c11/38b38a65-13c3-4f31-8ab0-78fd7b218c11.mp3"
    },
    {
      "id": "lux-aeterna",
      "type": "music",
      "title": "Lux Aeterna",
      "brand": "frankx",
      "status": "published",
      "tags": [
        "Neoclassical",
        "Orchestral",
        "Cinematic"
      ],
      "platform": "suno",
      "sunoId": "bf6d9c6a-7613-4562-8902-6380bfa04851",
      "sunoUrl": "https://suno.com/song/bf6d9c6a-7613-4562-8902-6380bfa04851",
      "genre": [
        "Neoclassical",
        "Orchestral",
        "Cinematic"
      ],
      "plays": 0,
      "section": "songs",
      "coverUrl": "https://cdn2.suno.ai/image_large_bf6d9c6a-7613-4562-8902-6380bfa04851.jpeg",
      "audioUrl": "https://vbmwpibfe0yzx3fd.public.blob.vercel-storage.com/music/bf6d9c6a-7613-4562-8902-6380bfa04851/bf6d9c6a-7613-4562-8902-6380bfa04851.mp3"
    }
  ]
}
