{
  "_description": "Arcanea Universe Music Inventory",
  "_brand": "arcanea",
  "_instructions": "Arcanea-themed Suno tracks and soundtracks for the fantasy universe",
  "_lastUpdated": "2026-01-23",
  "_count": 4,
  "_playlist": {
    "name": "Arcanean Choir",
    "url": "https://suno.com/playlist/898c6c67-1b25-495f-82ce-53d9139d9a25",
    "songs": 2
  },
  "tracks": [
    {
      "id": "arcanean-legends",
      "type": "music",
      "title": "Arcanean Legends",
      "description": "Fast-paced orchestral Arcanean pop rock mix with choir. Elvish orchestral with belting vocals in elvish language.",
      "brand": "arcanea",
      "status": "published",
      "tags": ["orchestral", "elvish", "choir", "epic", "arcanea"],
      "createdAt": "2025-01-01",
      "platform": "suno",
      "sunoId": "eb702834-22c6-44b3-8d5b-bba83c1e9801",
      "sunoUrl": "https://suno.com/song/eb702834-22c6-44b3-8d5b-bba83c1e9801",
      "duration": "3:24",
      "genre": ["pop-rock", "orchestral", "fantasy"],
      "mood": ["uplifting", "dramatic", "epic"],
      "promptUsed": "fast paced, orchestral, big drums, violin, pop rock, natural, uplifting, pop, arcanean pop rock mix with choir, elvish orchestral, arcanean choir belting vocal, elvish language, vocal, violin piano cross flutes nature sounds natural, female vocals, dramatic, feminine and male belting vocal, bariton and tenor layered with mezzo and sopran, sophisticated, uplifting epic feminine beauty extraordinary high notes cinematic choir high tones head voice dramatic sopran vocal mastery female vocals",
      "usageRights": "commercial",
      "universe": "arcanea"
    },
    {
      "id": "arcanean-starlight",
      "type": "music",
      "title": "Arcanean Starlight",
      "description": "Uplifting epic feminine beauty with extraordinary high notes. Arcanean arena rock mix with choir in invented elvish language.",
      "brand": "arcanea",
      "status": "published",
      "tags": ["orchestral", "elvish", "choir", "rock", "arcanea"],
      "createdAt": "2025-01-01",
      "platform": "suno",
      "sunoId": "5d17255b-f997-4f4c-82ea-9fa1d5aa982a",
      "sunoUrl": "https://suno.com/song/5d17255b-f997-4f4c-82ea-9fa1d5aa982a",
      "duration": "2:23",
      "genre": ["arena-rock", "orchestral", "fantasy"],
      "mood": ["uplifting", "dramatic", "sophisticated"],
      "promptUsed": "uplifting epic feminine beauty extraordinary high notes cinematic choir high tones head voice dramatic sopran vocal mastery female vocals, orchestral, natural, dramatic, sophisticated, uplifting, soul, arcanean arena rock mix with choir, bariton and tenor layered with mezzo and sopran, arcanean choir belting vocal, invented language, elvish orchestral, female vocals, rock, violin, vocal, feminine and male belting vocal, violin piano cross flutes nature sounds natural",
      "usageRights": "commercial",
      "universe": "arcanea"
    },
    {
      "id": "arcanea-awaken",
      "type": "music",
      "title": "Arcanea Awaken",
      "description": "Awakening theme for the Arcanea universe.",
      "brand": "arcanea",
      "status": "published",
      "tags": ["hook", "arcanea", "awakening"],
      "createdAt": "2025-01-01",
      "platform": "suno",
      "sunoUrl": "https://suno.com/@frankx/hook/279c5cdc-7eaf-4d8e-8d0d-19f990672194",
      "genre": ["fantasy", "orchestral"],
      "mood": ["epic", "awakening"],
      "usageRights": "commercial",
      "universe": "arcanea"
    },
    {
      "id": "arcanea-land-of-tomorrow",
      "type": "music",
      "title": "Arcanea Land of Tomorrow",
      "description": "Hopeful anthem for the Arcanea universe.",
      "brand": "arcanea",
      "status": "published",
      "tags": ["hook", "arcanea", "hopeful"],
      "createdAt": "2025-01-01",
      "platform": "suno",
      "sunoUrl": "https://suno.com/@frankx/hook/7d6a6dd7-93ee-4625-8814-fc1a55aa0de0",
      "genre": ["fantasy", "orchestral"],
      "mood": ["hopeful", "epic"],
      "usageRights": "commercial",
      "universe": "arcanea"
    }
  ]
}
